zapio/__init__.py
zapio/cli.py
zapio/assets/example.txt
zapio-0.0.1.dist-info/licenses/LICENSE
zapio-0.0.1.dist-info/METADATA
zapio-0.0.1.dist-info/WHEEL
zapio-0.0.1.dist-info/entry_points.txt
zapio-0.0.1.dist-info/top_level.txt
zapio-0.0.1.dist-info/RECORD
