Metadata-Version: 2.4
Name: zapio
Version: 0.0.1
Summary: platformio arduino embedded compiler
Home-page: https://github.com/zackees/zapio
Maintainer: Zachary Vorhies
License: BSD 3-Clause License
Keywords: template-python-cmd
Classifier: Programming Language :: Python :: 3
Requires-Python: >=3.10
License-File: LICENSE
Dynamic: home-page
Dynamic: license-file
Dynamic: maintainer
